{
  "id": "scenario-02-moderate-rain",
  "name": "F-16 vs S-400 (Moderate Rain)",
  "description": "Engagement with moderate precipitation field with evasive maneuver at engagement range",
  "timeStep": 1,
  "grid": {
    "width": 711,
    "height": 400,
    "resolution": 10
  },
  "platforms": {
    "sam": {
      "configId": "sam-s400",
      "position": {
        "x": 0,
        "y": 0
      },
      "heading": 0
    },
    "fighter": {
      "configId": "fighter-f16",
      "position": {
        "x": -80,
        "y": 0
      },
      "heading": 0,
      "flightPath": {
        "type": "straight"
      }
    }
  },
  "environment": {
    "precipitation": {
      "enabled": true,
      "nominalRainRate": 35,
      "nominalCellSize": 15,
      "nominalCoverage": 0.5,
      "alpha": 0.5,
      "maxRainRateCap": 45,
      "sigmoidK": 10
    }
  },
  "precipitationFieldImage": "precip_scenario-02-moderate-rain_1766220771429.jpg",
  "precipitationFieldOverlay": "precip_overlay_scenario-02-moderate-rain_1766220771783.jpg"
}